audio_synch_tool/__init__.py
audio_synch_tool/__main__.py
audio_synch_tool/mmc.py
audio_synch_tool/mvn.py
audio_synch_tool/plotters.py
audio_synch_tool/utils.py
audio_synch_tool/data/mvn_schema_adapted.xsd
audio_synch_tool/data/mvn_schema_original.xsd
audio_synch_tool/data/shift_left.png
audio_synch_tool/data/shift_right.png
audio_synch_tool/data/stretch_in.png
audio_synch_tool/data/stretch_out.png
audio_synch_tool/data/synch_and_save.png
audio_synch_tool/data/test_mmc_schema.jsd
audio_synch_tool-1.3.4.dist-info/LICENSE
audio_synch_tool-1.3.4.dist-info/METADATA
audio_synch_tool-1.3.4.dist-info/WHEEL
audio_synch_tool-1.3.4.dist-info/top_level.txt
audio_synch_tool-1.3.4.dist-info/RECORD
