Metadata-Version: 2.1
Name: audio-synch-tool
Version: 1.3.4
Summary: A matplotlib interactive gui to align signals with high         precision
Home-page: https://github.com/andres-fr/audio-synch-tool
Author: Andres FR
License: UNKNOWN
Platform: UNKNOWN
Classifier: Programming Language :: Python :: 3 :: Only
Classifier: License :: OSI Approved :: GNU General Public License v3 (GPLv3)
Classifier: Operating System :: OS Independent
